CGX/__init__.py
CGX/XJY/__init__.py
CGX/XJY/message.py
GD_1C302-0.1.dist-info/LICENSE.txt
GD_1C302-0.1.dist-info/METADATA
GD_1C302-0.1.dist-info/WHEEL
GD_1C302-0.1.dist-info/top_level.txt
GD_1C302-0.1.dist-info/RECORD
