Metadata-Version: 2.1
Name: GD-1C302
Version: 0.1
Summary: The members of our team are 肖俊毅,梁景洛 and 谭剑辉
Home-page: UNKNOWN
Author: GD
Author-email: UNKNOWN
License: UNKNOWN
Platform: UNKNOWN
